plazy/__init__.py
plazy/coding.py
plazy/data.py
plazy/file.py
plazy/singleton.py
plazy/timer.py
plazy-0.1.6.dist-info/LICENSE
plazy-0.1.6.dist-info/METADATA
plazy-0.1.6.dist-info/WHEEL
plazy-0.1.6.dist-info/top_level.txt
plazy-0.1.6.dist-info/RECORD
