Metadata-Version: 2.1
Name: plazy
Version: 0.1.6
Summary: Utilities for lazy Python developers
Home-page: https://github.com/kyzas/plazy
Download-URL: https://github.com/kyzas/plazy/tarball/master
Author: kyzas
Author-email: kyznano@gmail.com
Maintainer: kyzas
Maintainer-email: kyznano@gmail.com
License: MIT
Classifier: Development Status :: 4 - Beta
Classifier: License :: OSI Approved :: MIT License
Classifier: Topic :: Software Development :: Libraries :: Python Modules
Classifier: Intended Audience :: Developers
Classifier: Programming Language :: Python :: 3
Classifier: Programming Language :: Python :: 3.5
Classifier: Programming Language :: Python :: 3.6
Classifier: Programming Language :: Python :: 3.7
Classifier: Programming Language :: Python :: 3.8
Classifier: Programming Language :: Python :: 3.9
Classifier: Programming Language :: Python :: Implementation
Requires-Python: <4,>=3.5
License-File: LICENSE
